CHANGELOG.md
LICENSE
Makefile
README.md
package.json
requirements.txt
setup.py
tox.ini
ramjet/__init__.py
ramjet/__main__.py
ramjet/app.py
ramjet/engines.py
ramjet/patterns.py
ramjet.egg-info/PKG-INFO
ramjet.egg-info/SOURCES.txt
ramjet.egg-info/dependency_links.txt
ramjet.egg-info/entry_points.txt
ramjet.egg-info/requires.txt
ramjet.egg-info/top_level.txt
ramjet/libs/__init__.py
ramjet/libs/exceptions.py
ramjet/models/__init__.py
ramjet/models/__main__.py
ramjet/models/base.py
ramjet/models/mongo_dbs.py
ramjet/models/mysql_dbs.py
ramjet/settings/__init__.py
ramjet/settings/base.py
ramjet/settings/prd.py
ramjet/tasks/__init__.py
ramjet/tasks/email_proxy.py
ramjet/tasks/heart.py
ramjet/tasks/keyword.py
ramjet/tasks/webapps.py
ramjet/tasks/webdemo.py
ramjet/tasks/aws/__init__.py
ramjet/tasks/aws/rekognition.py
ramjet/tasks/monitors/__init__.py
ramjet/tasks/monitors/base.py
ramjet/tasks/monitors/ssl_cert.py
ramjet/tasks/twitter/__init__.py
ramjet/tasks/twitter/base.py
ramjet/tasks/twitter/crawler.py
ramjet/tasks/twitter/login.py
ramjet/utils/__init__.py
ramjet/utils/db.py
ramjet/utils/encrypt.py
ramjet/utils/jinja.py
ramjet/utils/mail.py