Metadata-Version: 1.1
Name: ramjet
Version: 1.8.1
Summary: Scripts Manager
Home-page: https://github.com/Laisky/ramjet
Author: Laisky
Author-email: ppcelery@gmail.com
License: MIT License
Keywords: aiohttp,trigger,utils
Platform: UNKNOWN
Classifier: Development Status :: 4 - Beta
Classifier: Development Status :: 4 - Beta
Classifier: Topic :: Software Development :: Libraries
Classifier: Environment :: Web Environment
Classifier: Intended Audience :: Developers
Classifier: License :: OSI Approved :: MIT License
Classifier: Operating System :: OS Independent
Classifier: Programming Language :: Python
Classifier: Programming Language :: Python :: 3.6
